README.md
setup.py
coreai/__init__.py
coreai/version.py
coreai/args/__init__.py
coreai/args/generation_args.py
coreai/infer/__init__.py
coreai/infer/qwenvl_infer.py
coreai/infer/qwenvl_sglang.py
coreai/infer/qwenvl_vllm.py
coreai/infer/vl_infer_base.py
coreai/models/__init__.py
coreai/models/firered/__init__.py
coreai/models/firered/fireredasr.py
coreai/models/firered/fireredasr_aed.py
coreai/models/firered/data/__init__.py
coreai/models/firered/data/asr_feat.py
coreai/models/firered/data/token_dict.py
coreai/models/firered/module/__init__.py
coreai/models/firered/module/adapter.py
coreai/models/firered/module/conformer_encoder.py
coreai/models/firered/module/transformer_decoder.py
coreai/models/firered/tokenizer/__init__.py
coreai/models/firered/tokenizer/aed_tokenizer.py
coreai/models/firered/tokenizer/llm_tokenizer.py
coreai/process/__init__.py
coreai/process/qwen_vision_process.py
coreai/serve/__init__.py
coreai/serve/api_schema.py
coreai/tasks/__init__.py
coreai/tasks/audio/__init__.py
coreai/tasks/audio/codecs/__init__.py
coreai/tasks/audio/codecs/focuscodec.py
coreai/tasks/audio/codecs/xcodec2/__init__.py
coreai/tasks/audio/codecs/xcodec2/configuration_bigcodec.py
coreai/tasks/audio/codecs/xcodec2/modeling_xcodec2.py
coreai/tasks/audio/codecs/xcodec2/module.py
coreai/tasks/audio/codecs/xcodec2/test.py
coreai/tasks/audio/codecs/xcodec2/vq/__init__.py
coreai/tasks/audio/codecs/xcodec2/vq/activations.py
coreai/tasks/audio/codecs/xcodec2/vq/blocks.py
coreai/tasks/audio/codecs/xcodec2/vq/bs_roformer5.py
coreai/tasks/audio/codecs/xcodec2/vq/codec_decoder.py
coreai/tasks/audio/codecs/xcodec2/vq/codec_decoder_vocos.py
coreai/tasks/audio/codecs/xcodec2/vq/codec_encoder.py
coreai/tasks/audio/codecs/xcodec2/vq/factorized_vector_quantize.py
coreai/tasks/audio/codecs/xcodec2/vq/module.py
coreai/tasks/audio/codecs/xcodec2/vq/residual_vq.py
coreai/tasks/audio/codecs/xcodec2/vq/unet.py
coreai/tasks/audio/codecs/xcodec2/vq/alias_free_torch/__init__.py
coreai_all.egg-info/PKG-INFO
coreai_all.egg-info/SOURCES.txt
coreai_all.egg-info/dependency_links.txt
coreai_all.egg-info/requires.txt
coreai_all.egg-info/top_level.txt
